<?xml version="1.0" encoding="UTF-8"?>

<database version="1.1" id="manga" language="ca"
	xmlns:xsi="http://www.w3.org/2001/XMLSchema-instance"
	xsi:noNamespaceSchemaLocation="file:///usr/share/games/freevial/databases/freevial-database.xsd">
  <information>
    <name>Mangues i còmics</name>
    <description>Preguntes sobre còmics i mangues</description>
    <destination>Persones amb coneixements de còmics</destination>
    <timestamp_creation>1189202400</timestamp_creation>
    <timestamp_modification>1208278969</timestamp_modification>

	<license>GPLv3</license>
	<url></url>
	<contact>info@freevial.org</contact>

    <authors>
      <author>Nil Oriol</author>
      <author>Marc Oriol</author>
      <author>Roger Pou</author>
    </authors>
  </information>
  <appearance>
    <image>categoria_mc.png</image>
    <sound>cmc.ogg</sound>
  </appearance>
  <questions>
    <question>
      <sentence>Quina diferència hi ha entre#en Dupond i en Dupont?</sentence>
      <author>NiliMarc</author>
      <comments></comments>
      <answers>
        <answer correct="true">Els bigotis</answer>
        <answer>Són exactament iguals</answer>
        <answer>L'un és esquerrà i l'altre és dretà</answer>
      </answers>
    </question>
    <question>
      <sentence>Quin és el déu de l'Obèlix?</sentence>
      <author>NiliMarc</author>
      <comments>Astèrix el gal#</comments>
      <answers>
        <answer correct="true">Tutatis</answer>
        <answer>Balenus</answer>
        <answer>Senglarus</answer>
      </answers>
    </question>
    <question>
      <sentence>Quants dits tenen els personatges#dels Simpsons?</sentence>
      <author>NiliMarc</author>
      <comments>Simpsons#</comments>
      <answers>
        <answer correct="true">4</answer>
        <answer>5</answer>
        <answer>3</answer>
      </answers>
    </question>
    <question>
      <sentence>Quin és l'únic lloc del món on#hi ha un Mazinger gegant?</sentence>
      <author>NiliMarc</author>
      <comments>Mazinger Z#A Tarragona s'hi anava a construir una urbanització (Mas de plata) que, com a reclam turístic, tenia un Mazinger gegant, però la urbanització no es va acabar i hi va quedar el Mazinger abandonat.</comments>
      <answers>
        <answer correct="true">Tarragona</answer>
        <answer>El Japó</answer>
        <answer>Corea</answer>
      </answers>
    </question>
    <question>
      <sentence>La personalitat secreta de#l'Increïble Hulk és...</sentence>
      <author>NiliMarc</author>
      <comments>L'Increïble Hulk#</comments>
      <answers>
        <answer correct="true">Bruce Banner</answer>
        <answer>Bruce Wayne</answer>
        <answer>Bruce Lee</answer>
      </answers>
    </question>
    <question>
      <sentence>Que la Yubaba mai et robi...</sentence>
      <author>NiliMarc</author>
      <comments>El viatge de Chihiro#La Yubaba és la bruixa dolenta del viatge de Chihiro, que dóna sobrenoms als seus treballadors perquè si obliden el seu nom ja no són ningú i els pot controlar. Per això en Haku li diu a la Chihiro que mai oblidi el seu nom.</comments>
      <answers>
        <answer correct="true">El nom</answer>
        <answer>La voluntat</answer>
        <answer>La imaginació</answer>
      </answers>
    </question>
    <question>
      <sentence>Com es diu en Superman#al seu planeta natal?</sentence>
      <author>NiliMarc</author>
      <comments>Superman#En Superman neix a Kriptó, essent el fill de Jor-El, un eminent científic i líder polític. En Superman fou batejat amb el nom de Kal-el</comments>
      <answers>
        <answer correct="true">Kal-el</answer>
        <answer>Jor-el</answer>
        <answer>Sar-el</answer>
      </answers>
    </question>
    <question>
      <sentence>Amb qui viu la Heidi?</sentence>
      <author>NiliMarc</author>
      <comments>Heidi#La seva tieta aconsegueix feina i l'envia a viure amb el seu avi, que ni tan sols coneixia</comments>
      <answers>
        <answer correct="true">Amb l'avi</answer>
        <answer>Amb els pares</answer>
        <answer>Sola</answer>
      </answers>
    </question>
    <question>
      <sentence>D'on surten o van tots els#autobusos i metros del Superlópez?</sentence>
      <author>NiliMarc</author>
      <comments>Superlópez#</comments>
      <answers>
        <answer correct="true">El Masnou</answer>
        <answer>L'Hospitalet</answer>
        <answer>Barcelona</answer>
      </answers>
    </question>
    <question>
      <sentence>Què menja en Popeye#per tornar-se fort?</sentence>
      <author>NiliMarc</author>
      <comments>Popeye#Quan en Popeye necessita ser fort menja espinacs. Cal tenir en compte que durant molt de temps es va creure que els espinacs contenien molt més ferro del que en realitat tenen, perquè en una classificació havien col·locat malament la coma dels decimals.</comments>
      <answers>
        <answer correct="true">Espinacs</answer>
        <answer>Alls</answer>
        <answer>Cebes</answer>
      </answers>
    </question>
    <question>
      <sentence>Quin poder especial#té en Batman?</sentence>
      <author>NiliMarc</author>
      <comments>Batman#L'únic poder que realment té és ser fill de papà.</comments>
      <answers>
        <answer correct="true">Cap</answer>
        <answer>Pot volar com els ratpenats</answer>
        <answer>Sent ultrasons</answer>
      </answers>
    </question>
    <question>
      <sentence>Com es diu el planeta natal#d'en Superman?</sentence>
      <author>NiliMarc</author>
      <comments>Superman#Superman neix a Kriptó, essent el fill de Jor-El, un eminent científic i líder polític. Superman fou batejat amb el nom de Kal-el</comments>
      <answers>
        <answer correct="true">Criptó</answer>
        <answer>Terra</answer>
        <answer>K-pax</answer>
      </answers>
    </question>
    <question>
      <sentence>L'Spiderman es transforma en#superheroi després que...</sentence>
      <author>NiliMarc</author>
      <comments>Spiderman#</comments>
      <answers>
        <answer correct="true">El mossegui una aranya</answer>
        <answer>Entri en contacte amb un meteorit</answer>
        <answer>Una radiació estranya l'afecti</answer>
      </answers>
    </question>
    <question>
      <sentence>Els mangues es llegeixen...</sentence>
      <author>NiliMarc</author>
      <comments>Es manté la direcció original de les vinyetes.</comments>
      <answers>
        <answer correct="true">De dreta a esquerra i de dalt a baix</answer>
        <answer>D'esquerra a dreta i de baix a dalt</answer>
        <answer>D'esquerra a dreta i de dalt a baix</answer>
      </answers>
    </question>
    <question>
      <sentence>Quin secret té l'Arale?</sentence>
      <author>NiliMarc</author>
      <comments>Dr.Slump#</comments>
      <answers>
        <answer correct="true">És un robot</answer>
        <answer>És una superheroïna</answer>
        <answer>Ve d'un altre planeta</answer>
      </answers>
    </question>
    <question>
      <sentence>Què fa en López a l'oficina?</sentence>
      <author>NiliMarc</author>
      <comments>Superlópez#La personalitat secreta d'en Superlópez és una feina molt dura.</comments>
      <answers>
        <answer correct="true">Fa ocellets de paper</answer>
        <answer>Juga amb el boli</answer>
        <answer>Treballa</answer>
      </answers>
    </question>
    <question>
      <sentence>Els “dolents” d'Evangelion són...</sentence>
      <author>NiliMarc</author>
      <comments>Evangelion#</comments>
      <answers>
        <answer correct="true">Àngels</answer>
        <answer>Dimonis</answer>
        <answer>Robots</answer>
      </answers>
    </question>
    <question>
      <sentence>Itxigo Kurosaki és un#noi normal que...</sentence>
      <author>NiliMarc</author>
      <comments>Bleach#Itxigo Kurosaki no és un noi de quinze anys normal i corrent... pot veure esperits i té un contacte innat amb el més enllà, del que traurà profit després de conèixer un shinigami (àngel de la mort) que li proporciona una espasa a joc amb les seves habilitats</comments>
      <answers>
        <answer correct="true">Veu fantasmes</answer>
        <answer>Lluita contra monstres</answer>
        <answer>Vol controlar el món</answer>
      </answers>
    </question>
    <question>
      <sentence>Quin és el somni d'en Naruto?</sentence>
      <author>NiliMarc</author>
      <comments>Naruto#Quan Naruto neix li segellen un monstre a dins, tot el poble li té por i per això el deixen de banda, per això en Naruto vol ser el Hokaje, el títol més important dels ninges.</comments>
      <answers>
        <answer correct="true">Convertir-se en Hokaje</answer>
        <answer>Ser el millor ninja</answer>
        <answer>Venjar-se del seu germà gran</answer>
      </answers>
    </question>
    <question>
      <sentence>Què menja en Musculman#per tornar-se fort?</sentence>
      <author>NiliMarc</author>
      <comments>Musculman#</comments>
      <answers>
        <answer correct="true">Alls</answer>
        <answer>Cebes</answer>
        <answer>Espinacs</answer>
      </answers>
    </question>
    <question>
      <sentence>Com anomenen en#Vash l'Estampida?</sentence>
      <author>NiliMarc</author>
      <comments>Trigun#Després de la catastròfica arribada al planeta, i havent perdut durant el viatge la seva estimada, en Vash decideix que no permetrà que el seu germà Knives faci mal a ningú més. Però, com que ell és un alienígena molt poderós, destrueix sense voler una ciutat. Per això el seu cap passa a valdre 60.000.000.000$$ i rep un nou nom: "Tifó Humanoide".</comments>
      <answers>
        <answer correct="true">Tifó humanoide</answer>
        <answer>L'home dels 60.000.000$$</answer>
        <answer>L'home que va foradar la lluna</answer>
      </answers>
    </question>
    <question>
      <sentence>Quin problema té en Ranma#amb l'aigua?</sentence>
      <author>NiliMarc</author>
      <comments>Ranma#En Ranma entrenava Jusenkyo per arribar a ser el millor lluitador d'arts marcials del món, allà ell i el seu pare queden maleïts perquè cauen a l'aigua i quan es mullen es transformen en noia (en Ranma) i panda (el seu pare).</comments>
      <answers>
        <answer correct="true">Es transforma en noia</answer>
        <answer>Es converteix en mico gegant</answer>
        <answer>Es transforma en panda</answer>
      </answers>
    </question>
    <question>
      <sentence>On va néixer en Marco?</sentence>
      <author>NiliMarc</author>
      <comments>Marco#En un poble italià, al peu de les muntanyes, hi viu el nostre amic Marco</comments>
      <answers>
        <answer correct="true">En un poble italià</answer>
        <answer>En un poble rus</answer>
        <answer>En un poble romanès</answer>
      </answers>
    </question>
    <question>
      <sentence>De quin material està fet#el Mazinger Z?</sentence>
      <author>NiliMarc</author>
      <comments>Mazinger Z# El centre d'investigacions fotoatòmiques va descobrir aquest material per poder crear el robot Mazinger Z.</comments>
      <answers>
        <answer correct="true">Japànium (aliatge Z)</answer>
        <answer>Mazingànium (aliatge final)</answer>
        <answer>Titànium (reforçat)</answer>
      </answers>
    </question>
    <question>
      <sentence>Quina és la tècnica definitiva#de la Ginger Inokuma?</sentence>
      <author>NiliMarc</author>
      <comments>Cinturó Negre#La Ginger acaba quasi sempre els seus combats amb una tècnica anomenada "ippon seoi nage", que és una de les tècniques requerides per al cinturó groc. </comments>
      <answers>
        <answer correct="true">Ippon seoi nage</answer>
        <answer>L'atac d'en Kaito</answer>
        <answer>Reigan</answer>
      </answers>
    </question>
    <question>
      <sentence>Què vol dir Kame en japonès?</sentence>
      <author>NiliMarc</author>
      <comments>Bola de Drac#Follet tortuga és en la versió original Kame Sen'nin i el típic "kame hame ha" voldria dir "gran onada de corrent tortuga".</comments>
      <answers>
        <answer correct="true">Tortuga</answer>
        <answer>Energia</answer>
        <answer>Bola</answer>
      </answers>
    </question>
    <question>
      <sentence>La relació entre en Kyo#i en Yuki és...</sentence>
      <author>NiliMarc</author>
      <comments>Fruits Basket#Yuki és la rata de la famílila Soma, mentre que Kyo és el Gat de la llegenda del zodíac xinès (però el gat va ser enganyat per la rata perquè no anés a la festa, i per això el gat odia tant la rata).</comments>
      <answers>
        <answer correct="true">Es persegueixen com un gat i una rata</answer>
        <answer>S'odien</answer>
        <answer>Són bons amics</answer>
      </answers>
    </question>
    <question>
      <sentence>En Mortadel·lo perd els cabells# perquè..</sentence>
      <author>NiliMarc</author>
      <comments>Mortadel·lo i Filemó#A La història de Mortadel·lo i Filemó s'explica que quan en Mortadel·lo era un grenyes que tothom coneixia, el doctor Bacteri, que era barber, li va posar una cosa perquè no s'hagués de preocupar pels cabells mai més...</comments>
      <answers>
        <answer correct="true">El doctor Bacteri l'enganya</answer>
        <answer>Es disfressa de vell i no es pot treure#la calba falsa</answer>
        <answer>Un indi l'hi arrenca</answer>
      </answers>
    </question>
    <question>
      <sentence>12 dels membres de la família#Soma es transformen en...</sentence>
      <author>NiliMarc</author>
      <comments>Fruits Basket#Es transformen quan es cansen massa o els toca una persona del sexe oposat que no sigui integrant de la família, per això són una família molt tancada.</comments>
      <answers>
        <answer correct="true">Els 12 animals del zodíac xinès</answer>
        <answer>Els 12 apòstols</answer>
        <answer>Una dotzena d'ous</answer>
      </answers>
    </question>
    <question>
      <sentence>A què es dedica en Sergi Grapes?</sentence>
      <author>NiliMarc</author>
      <comments>Sergi Grapes# Encara que estigui sempre fent invents, bestieses o dormint, el seu veritable ofici és el de repartidor de cartes.</comments>
      <answers>
        <answer correct="true">"Mindundi" d'oficina</answer>
        <answer>Jugador de futbol</answer>
        <answer>Cambrer</answer>
      </answers>
    </question>
    <question>
      <sentence>A quin planeta va néixer#en Cor Petit?</sentence>
      <author>NiliMarc</author>
      <comments>Bola de Drac# El Cor Petit/déu prové de Namek.</comments>
      <answers>
        <answer correct="true">Namek</answer>
        <answer>La terra</answer>
        <answer>Vegeta</answer>
      </answers>
    </question>
    <question>
      <sentence>En Kakarot és...</sentence>
      <author>NiliMarc</author>
      <comments>Bola de Drac Z#En Vegeta, el príncep dels superguerrers, sempre anomena en Goku Kakarot, ja que era el seu nom original al planeta Vegeta, que és on va néixer (el planeta Vegeta va ser destruït per en Frezeer).</comments>
      <answers>
        <answer correct="true">En Goku</answer>
        <answer>En Ràdix</answer>
        <answer>En Vegeta</answer>
      </answers>
    </question>
    <question>
      <sentence>Les fruites del diable et donen#un poder, però..</sentence>
      <author>NiliMarc</author>
      <comments>One Piece#Les fruites del diable donen els poders a tots els grans capitans pirates de la red line.</comments>
      <answers>
        <answer correct="true">No pots nedar</answer>
        <answer>Quan et toca la llum de la lluna#et converteixes</answer>
        <answer>No et pot tocar la llum del sol</answer>
      </answers>
    </question>
    <question>
      <sentence>La mà dimoni del Sawamura#es converteix en...</sentence>
      <author>NiliMarc</author>
      <comments>Midori No Hibi#Sawamura ha passat 17 anys i 2 mesos sense xicota, amb un rècord històric al seu institut de 20 carabasses; quan ja ho dóna tot per perdut, sent una veu femenina molt a prop del seu cap... Surt de la seva mà.</comments>
      <answers>
        <answer correct="true">Una noia</answer>
        <answer>Una destral</answer>
        <answer>Un ganxo</answer>
      </answers>
    </question>
    <question>
      <sentence>Monkey D.Luffy somia en...</sentence>
      <author>NiliMarc</author>
      <comments>One Piece#Monkey D.Luffy és un noi de poble costaner, el seu somni de tota la vida ha estat ser pirata, ja que veia com els pirates amarraven la barca allí i s'ho passaven molt bé. Però després de conèixer un noi molt covard a una illa deserta controlada per una bruixa pirata, vol, a més, ser-ne el rei.</comments>
      <answers>
        <answer correct="true">Ser el rei dels pirates</answer>
        <answer>Una quantitat inacabable de menjar</answer>
        <answer>Tenir la tripulació més gran del món</answer>
      </answers>
    </question>
    <question>
      <sentence>Com és diu el 4t "espada" de la serie Bleach?</sentence>
      <author>RogerPou</author>
      <comments></comments>
      <answers>
        <answer correct="true">Ulquiorra</answer>
        <answer>Grimjow</answer>
        <answer>Yammi</answer>
      </answers>
    </question>
    <question>
      <sentence>Qui és el pare d'en Naruto?</sentence>
      <author>RogerPou</author>
      <comments></comments>
      <answers>
        <answer correct="true">4t hokage, Yondaime</answer>
        <answer>Zetsu d'Akatsuki</answer>
        <answer>Kakashi</answer>
      </answers>
    </question>
    <question>
      <sentence>Quin és el nom de la segona i definitiva lliberació de la Zanpakou d'un shinigami?</sentence>
      <author>RogerPou</author>
      <comments></comments>
      <answers>
        <answer correct="true">Bankai</answer>
        <answer>Shipon</answer>
        <answer>Bakuya</answer>
      </answers>
    </question>
    <question>
      <sentence>Com es diu la noia que li agrada a en Naruto?</sentence>
      <author>JoanSanchez</author>
      <comments></comments>
      <answers>
        <answer correct="true">Sakura</answer>
        <answer>Shakira</answer>
        <answer>Hinata</answer>
      </answers>
    </question>
    <question>
      <sentence>Que passa en el primer capítol de Gantz?</sentence>
      <author>Gimcana</author>
      <comments></comments>
      <answers>
        <answer correct="true">Moren els protagonistes.</answer>
        <answer>Presenten els personatges.</answer>
        <answer>És un flashback.</answer>
      </answers>
    </question>
  </questions>
</database>
